Metadata-Version: 2.1
Name: odoo-addon-website_sale_stock_order_cancel
Version: 15.0.1.0.0.2
Summary: Enhances website sale order cancellation by blocking it when related stock pickings are done.
Home-page: https://github.com/OCA/e-commerce
Author: APSL-Nagarro, Odoo Community Association (OCA)
Author-email: support@odoo-community.org
License: AGPL-3
Classifier: Programming Language :: Python
Classifier: Framework :: Odoo
Classifier: Framework :: Odoo :: 15.0
Classifier: License :: OSI Approved :: GNU Affero General Public License v3
Requires-Python: >=3.8
Requires-Dist: odoo-addon-website-sale-order-cancel<15.1dev,>=15.0dev
Requires-Dist: odoo<15.1dev,>=15.0a
